{
	"credit": "Made with Blockbench",
	"parent": "block/block",
	"ambientocclusion": false,
	"texture_size": [32, 32],
	"textures": {
		"2": "hexerei:block/witch_hazel_altar_top",
		"3": "hexerei:block/witch_hazel_altar_parts",
		"particle": "hexerei:particle/witch_hazel_altar_particle"
	},
	"elements": [
		{
			"from": [0, 12, 0],
			"to": [16, 16, 16],
			"rotation": {"angle": 0, "axis": "x", "origin": [8, 14, 8]},
			"faces": {
				"north": {"uv": [0, 12, 8, 14], "texture": "#3"},
				"east": {"uv": [0, 14, 8, 16], "texture": "#3"},
				"south": {"uv": [8, 12, 16, 14], "texture": "#3"},
				"west": {"uv": [8, 14, 16, 16], "texture": "#3"},
				"up": {"uv": [16, 16, 0, 0], "texture": "#2"},
				"down": {"uv": [16, 0, 0, 16], "texture": "#2"}
			}
		},
		{
			"from": [12, 0, 1],
			"to": [15, 12, 4],
			"rotation": {"angle": 0, "axis": "y", "origin": [8, -4, 8]},
			"faces": {
				"north": {"uv": [0, 0, 1.5, 6], "texture": "#3"},
				"east": {"uv": [1.5, 0, 3, 6], "texture": "#3"},
				"south": {"uv": [3, 0, 4.5, 6], "texture": "#3"},
				"west": {"uv": [4.5, 0, 6, 6], "texture": "#3"},
				"up": {"uv": [1.5, 10.5, 0, 9], "texture": "#3"},
				"down": {"uv": [3, 9, 1.5, 10.5], "texture": "#3"}
			}
		},
		{
			"from": [12, 0, 12],
			"to": [15, 12, 15],
			"rotation": {"angle": 0, "axis": "y", "origin": [8, -4, 8]},
			"faces": {
				"north": {"uv": [4.5, 0, 6, 6], "texture": "#3"},
				"east": {"uv": [0, 0, 1.5, 6], "texture": "#3"},
				"south": {"uv": [1.5, 0, 3, 6], "texture": "#3"},
				"west": {"uv": [3, 0, 4.5, 6], "texture": "#3"},
				"up": {"uv": [1.5, 10.5, 0, 9], "rotation": 90, "texture": "#3"},
				"down": {"uv": [3, 9, 1.5, 10.5], "rotation": 270, "texture": "#3"}
			}
		},
		{
			"from": [1, 0, 12],
			"to": [4, 12, 15],
			"rotation": {"angle": 0, "axis": "y", "origin": [8, -4, 8]},
			"faces": {
				"north": {"uv": [3, 0, 4.5, 6], "texture": "#3"},
				"east": {"uv": [4.5, 0, 6, 6], "texture": "#3"},
				"south": {"uv": [0, 0, 1.5, 6], "texture": "#3"},
				"west": {"uv": [1.5, 0, 3, 6], "texture": "#3"},
				"up": {"uv": [1.5, 10.5, 0, 9], "rotation": 180, "texture": "#3"},
				"down": {"uv": [3, 9, 1.5, 10.5], "rotation": 180, "texture": "#3"}
			}
		},
		{
			"from": [1, 0, 1],
			"to": [4, 12, 4],
			"rotation": {"angle": 0, "axis": "y", "origin": [8, -4, 8]},
			"faces": {
				"north": {"uv": [1.5, 0, 3, 6], "texture": "#3"},
				"east": {"uv": [3, 0, 4.5, 6], "texture": "#3"},
				"south": {"uv": [4.5, 0, 6, 6], "texture": "#3"},
				"west": {"uv": [0, 0, 1.5, 6], "texture": "#3"},
				"up": {"uv": [1.5, 10.5, 0, 9], "rotation": 270, "texture": "#3"},
				"down": {"uv": [3, 9, 1.5, 10.5], "rotation": 90, "texture": "#3"}
			}
		},
		{
			"from": [0, 6, 1],
			"to": [16, 9, 4],
			"rotation": {"angle": 0, "axis": "y", "origin": [8, 7.5, 8]},
			"faces": {
				"north": {"uv": [5.5, 6, 9.5, 7.5], "texture": "#3"},
				"east": {"uv": [7, 7.5, 8.5, 9], "texture": "#3"},
				"south": {"uv": [0, 7.5, 4, 9], "texture": "#3"},
				"west": {"uv": [8.5, 7.5, 10, 9], "texture": "#3"},
				"up": {"uv": [11.5, 3, 7.5, 1.5], "texture": "#3"},
				"down": {"uv": [11.5, 3, 7.5, 4.5], "texture": "#3"}
			}
		},
		{
			"from": [12, 6, 0],
			"to": [15, 9, 16],
			"rotation": {"angle": 0, "axis": "y", "origin": [8, 7.5, 8]},
			"faces": {
				"north": {"uv": [8.5, 7.5, 10, 9], "texture": "#3"},
				"east": {"uv": [5.5, 6, 9.5, 7.5], "texture": "#3"},
				"south": {"uv": [7, 7.5, 8.5, 9], "texture": "#3"},
				"west": {"uv": [0, 7.5, 4, 9], "texture": "#3"},
				"up": {"uv": [11.5, 3, 7.5, 1.5], "rotation": 90, "texture": "#3"},
				"down": {"uv": [11.5, 3, 7.5, 4.5], "rotation": 270, "texture": "#3"}
			}
		},
		{
			"from": [0, 6, 12],
			"to": [16, 9, 15],
			"rotation": {"angle": 0, "axis": "y", "origin": [8, 7.5, 8]},
			"faces": {
				"north": {"uv": [0, 7.5, 4, 9], "texture": "#3"},
				"east": {"uv": [8.5, 7.5, 10, 9], "texture": "#3"},
				"south": {"uv": [5.5, 6, 9.5, 7.5], "texture": "#3"},
				"west": {"uv": [7, 7.5, 8.5, 9], "texture": "#3"},
				"up": {"uv": [11.5, 3, 7.5, 1.5], "rotation": 180, "texture": "#3"},
				"down": {"uv": [11.5, 3, 7.5, 4.5], "rotation": 180, "texture": "#3"}
			}
		},
		{
			"from": [1, 6, 0],
			"to": [4, 9, 16],
			"rotation": {"angle": 0, "axis": "y", "origin": [8, 7.5, 8]},
			"faces": {
				"north": {"uv": [7, 7.5, 8.5, 9], "texture": "#3"},
				"east": {"uv": [0, 7.5, 4, 9], "texture": "#3"},
				"south": {"uv": [8.5, 7.5, 10, 9], "texture": "#3"},
				"west": {"uv": [5.5, 6, 9.5, 7.5], "texture": "#3"},
				"up": {"uv": [11.5, 3, 7.5, 1.5], "rotation": 270, "texture": "#3"},
				"down": {"uv": [11.5, 3, 7.5, 4.5], "rotation": 90, "texture": "#3"}
			}
		}
	],
	"display": {
		"firstperson_righthand": {
			"rotation": [0, 135, 0],
			"scale": [0.4, 0.4, 0.4]
		}
	},
	"groups": [
		{
			"name": "VoxelShapes",
			"origin": [10, -5, 0],
			"color": 0,
			"children": [0, 1, 2, 3, 4, 5, 6, 7, 8]
		}
	]
}