{
  "parent": "minecraft:recipes/root",
  "criteria": {
    "give_recipe": {
      "conditions": {
        "items": [
          {
            "items": [
              "hexerei:polished_mahogany_stairs"
            ]
          }
        ]
      },
      "trigger": "minecraft:inventory_changed"
    },
    "has_block": {
      "conditions": {
        "items": [
          {
            "items": [
              "hexerei:polished_mahogany_stairs"
            ]
          }
        ]
      },
      "trigger": "minecraft:inventory_changed"
    }
  },
  "requirements": [
    [
      "has_block"
    ],
    [
      "give_recipe"
    ]
  ],
  "rewards": {
    "recipes": [
      "minecraft:woodcutting/mahogany/polished_mahogany_slab_from_polished_mahogany_stairs_woodcutting_combine"
    ]
  }
}